wagtail_references/__init__.py
wagtail_references/admin.py
wagtail_references/admin_urls.py
wagtail_references/apps.py
wagtail_references/blocks.py
wagtail_references/edit_handlers.py
wagtail_references/fields.py
wagtail_references/forms.py
wagtail_references/models.py
wagtail_references/permissions.py
wagtail_references/serializers.py
wagtail_references/signal_handlers.py
wagtail_references/urls.py
wagtail_references/wagtail_hooks.py
wagtail_references/migrations/0001_initial.py
wagtail_references/migrations/__init__.py
wagtail_references/views/__init__.py
wagtail_references/views/api.py
wagtail_references/views/chooser.py
wagtail_references/views/references.py
wagtail_references/views/serve.py
wagtail_references-0.0.1.dist-info/LICENSE
wagtail_references-0.0.1.dist-info/METADATA
wagtail_references-0.0.1.dist-info/WHEEL
wagtail_references-0.0.1.dist-info/top_level.txt
wagtail_references-0.0.1.dist-info/RECORD
