Metadata-Version: 2.1
Name: wagtail-references
Version: 0.0.1
Summary: BibTeX references for Wagtail
Home-page: https://github.com/thclark/wagtail_references
Author: thclark
Author-email: withheld.find@me.at.github.com
License: MIT
Keywords: wagtail,django,events
Platform: UNKNOWN
Classifier: Development Status :: 4 - Beta
Classifier: Intended Audience :: Developers
Classifier: Topic :: Software Development :: Libraries :: Python Modules
Classifier: License :: OSI Approved :: MIT License
Classifier: Programming Language :: Python :: 3.6
Classifier: Programming Language :: Python :: 3.7
Classifier: Operating System :: OS Independent
Requires-Dist: wagtail (>=2.3)
Requires-Dist: isoweek (==1.3.3)
Requires-Dist: python-dateutil (>=2.6.0)
Requires-Dist: bibtexparser (>=1.1.0)
